mylib_030/__init__.py
mylib_030-0.1.dist-info/LICENSE.txt
mylib_030-0.1.dist-info/METADATA
mylib_030-0.1.dist-info/WHEEL
mylib_030-0.1.dist-info/top_level.txt
mylib_030-0.1.dist-info/RECORD
